pulumi_clevercloud/__init__.py
pulumi_clevercloud/_utilities.py
pulumi_clevercloud/provider.py
pulumi_clevercloud/pulumi-plugin.json
pulumi_clevercloud/py.typed
pulumi_clevercloud/addons/__init__.py
pulumi_clevercloud/addons/cellar.py
pulumi_clevercloud/addons/elasticsearch.py
pulumi_clevercloud/addons/mongo_db.py
pulumi_clevercloud/addons/my_sql.py
pulumi_clevercloud/addons/postgre_sql.py
pulumi_clevercloud/addons/redis.py
pulumi_clevercloud/applications/__init__.py
pulumi_clevercloud/applications/docker.py
pulumi_clevercloud/applications/go_app.py
pulumi_clevercloud/applications/java.py
pulumi_clevercloud/applications/node_js.py
pulumi_clevercloud/applications/php.py
pulumi_clevercloud/applications/python.py
pulumi_clevercloud/applications/ruby.py
pulumi_clevercloud/applications/static.py
pulumi_clevercloud/config/__init__.py
pulumi_clevercloud/config/__init__.pyi
pulumi_clevercloud/config/vars.py
pulumi_clevercloud/datasources/__init__.py
pulumi_clevercloud/datasources/get_addon.py
pulumi_clevercloud/datasources/get_application.py
pulumi_clevercloud-0.0.19.dist-info/METADATA
pulumi_clevercloud-0.0.19.dist-info/WHEEL
pulumi_clevercloud-0.0.19.dist-info/top_level.txt
pulumi_clevercloud-0.0.19.dist-info/RECORD
