Metadata-Version: 2.4
Name: pulumi_clevercloud
Version: 0.0.19
Summary: The Clever Cloud provider for Pulumi lets you manage Clever Cloud resources.
Home-page: https://www.clever-cloud.com
License: Apache-2.0
Project-URL: Repository, https://github.com/clevercloud/pulumi-clevercloud
Keywords: pulumi clevercloud clever-cloud paas category/cloud
Requires-Python: >=3.9
Requires-Dist: parver>=0.2.1
Requires-Dist: pulumi<4.0.0,>=3.165.0
Requires-Dist: semver>=2.8.1
Requires-Dist: typing-extensions<5,>=4.11; python_version < "3.11"
Dynamic: description
Dynamic: description-content-type
Dynamic: home-page
Dynamic: keywords
Dynamic: license
Dynamic: project-url
Dynamic: requires-dist
Dynamic: requires-python
Dynamic: summary
